<ServiceRequest>
  <data>
    <WasScanSchedule>
      <notification>
        <active>true</active>
        <delay>
          <nb>4</nb>
           <scale>DAY</scale>
        </delay>
        <recipients>
             <set>
	   <EmailAddress><![CDATA[devops@aenetworks.com]]></EmailAddress>
	   <EmailAddress><![CDATA[greg.taylor@aenetworks.com]]></EmailAddress>
	   <EmailAddress><![CDATA[gregtaylor999@gmail.com]]></EmailAddress>
             </set>
        </recipients>
        <message><![CDATA[The schedule notification message]]></message>
        </notification>
      </WasScanSchedule>
   </data>
</ServiceRequest>
